lasp_packets/__init__.py
lasp_packets/csvdef.py
lasp_packets/parser.py
lasp_packets/xtcedef.py
lasp_packets-3.0.dist-info/WHEEL
lasp_packets-3.0.dist-info/LICENSE.txt
lasp_packets-3.0.dist-info/METADATA
lasp_packets-3.0.dist-info/RECORD
