Metadata-Version: 2.1
Name: lasp-packets
Version: 3.0
Summary: CCSDS packet decoding library
License: BSD-3-Clause
Author: Gavin Medley
Author-email: gavin.medley@lasp.colorado.edu
Maintainer: Gavin Medley
Maintainer-email: gavin.medley@lasp.colorado.edu
Requires-Python: >=3.7,<3.12
Classifier: License :: OSI Approved :: BSD License
Classifier: Programming Language :: Python :: 3
Classifier: Programming Language :: Python :: 3.7
Classifier: Programming Language :: Python :: 3.8
Classifier: Programming Language :: Python :: 3.9
Classifier: Programming Language :: Python :: 3.10
Classifier: Programming Language :: Python :: 3.11
Requires-Dist: bitstring (>=3.0.0)
